onedrive_upload/__init__.py
onedrive_upload/core.py
onedrive_upload-1.0.0.dist-info/METADATA
onedrive_upload-1.0.0.dist-info/WHEEL
onedrive_upload-1.0.0.dist-info/top_level.txt
onedrive_upload-1.0.0.dist-info/RECORD
