Metadata-Version: 2.4
Name: onedrive-upload
Version: 1.0.0
Summary: Simple OneDrive upload for company-wide access
Author: Your Name
Author-email: Yash Edake <yash.edake@maxspike.in>
License: MIT
Project-URL: Homepage, https://github.com/yourusername/onedrive-upload
Keywords: onedrive,microsoft,graph,upload,azure
Classifier: Development Status :: 4 - Beta
Classifier: Intended Audience :: Developers
Classifier: License :: OSI Approved :: MIT License
Classifier: Programming Language :: Python :: 3
Classifier: Programming Language :: Python :: 3.8
Classifier: Programming Language :: Python :: 3.9
Classifier: Programming Language :: Python :: 3.10
Classifier: Programming Language :: Python :: 3.11
Classifier: Programming Language :: Python :: 3.12
Requires-Python: >=3.8
Requires-Dist: msal>=1.24.0
Requires-Dist: requests>=2.28.0
Requires-Dist: python-dotenv>=1.0.0
Dynamic: author
Dynamic: requires-python
